fiscalapi/__init__.py
fiscalapi/models/__init__.py
fiscalapi/models/common_models.py
fiscalapi/models/fiscalapi_models.py
fiscalapi/services/__init__.py
fiscalapi/services/api_key_service.py
fiscalapi/services/base_service.py
fiscalapi/services/catalog_service.py
fiscalapi/services/download_catalog_service.py
fiscalapi/services/download_request_service.py
fiscalapi/services/download_rule_service.py
fiscalapi/services/fiscalapi_client.py
fiscalapi/services/invoice_service.py
fiscalapi/services/people_service.py
fiscalapi/services/product_service.py
fiscalapi/services/tax_file_servive.py
fiscalapi-4.0.270.dist-info/licenses/LICENSE.txt
fiscalapi-4.0.270.dist-info/METADATA
fiscalapi-4.0.270.dist-info/WHEEL
fiscalapi-4.0.270.dist-info/top_level.txt
fiscalapi-4.0.270.dist-info/RECORD
