Metadata-Version: 2.4
Name: fiscalapi
Version: 4.0.270
Summary: Genera facturas CFDI válidas ante el SAT consumiendo el API de https://www.fiscalapi.com
Home-page: https://www.fiscalapi.com
Author: Fiscalapi
Author-email: contacto@fiscalapi.com
License: MPL-2.0
Keywords: factura,cfdi,facturacion,mexico,sat,fiscalapi
Classifier: Development Status :: 5 - Production/Stable
Classifier: Intended Audience :: Developers
Classifier: License :: OSI Approved :: Mozilla Public License 2.0 (MPL 2.0)
Classifier: Programming Language :: Python :: 3.7
Classifier: Topic :: Office/Business :: Financial
Requires-Python: >=3.7
License-File: LICENSE.txt
Requires-Dist: pydantic>=2.0.0
Requires-Dist: requests>=2.0.0
Requires-Dist: urllib3>=1.0.0
Requires-Dist: certifi>=2023.0.0
Requires-Dist: email_validator>=2.2.0
Dynamic: author
Dynamic: author-email
Dynamic: classifier
Dynamic: description
Dynamic: description-content-type
Dynamic: home-page
Dynamic: keywords
Dynamic: license
Dynamic: license-file
Dynamic: requires-dist
Dynamic: requires-python
Dynamic: summary
